{
  "watchlist": [
    {
      "ticker": "POET",
      "price": 10.73,
      "previousClose": 12.09,
      "volume": 17242893,
      "marketCap": 1851948672,
      "rsi14": 38.9,
      "bbPercent": 0.139,
      "priceFetchedAt": "2026-06-24 00:28 EDT"
    },
    {
      "ticker": "CDE",
      "price": 16.32,
      "previousClose": 17.47,
      "volume": 38589589,
      "marketCap": 16818323456,
      "rsi14": 37.0,
      "bbPercent": 0.209,
      "priceFetchedAt": "2026-06-24 00:28 EDT"
    },
    {
      "ticker": "CRDO",
      "price": 272.005,
      "previousClose": 302.52,
      "volume": 10313821,
      "marketCap": 50722922496,
      "rsi14": 59.7,
      "bbPercent": 0.832,
      "priceFetchedAt": "2026-06-24 00:28 EDT"
    },
    {
      "ticker": "SPCX",
      "price": 156.11,
      "previousClose": 154.6,
      "volume": 153240080,
      "marketCap": 2056622309376,
      "rsi14": null,
      "bbPercent": null,
      "priceFetchedAt": "2026-06-24 00:28 EDT"
    },
    {
      "ticker": "NBIS",
      "price": 275.25,
      "previousClose": 283.61,
      "volume": 18422605,
      "marketCap": 69885476864,
      "rsi14": 54.7,
      "bbPercent": 0.785,
      "priceFetchedAt": "2026-06-24 00:28 EDT"
    },
    {
      "ticker": "FLY",
      "price": 27.21,
      "previousClose": 28.96,
      "volume": 5154047,
      "marketCap": 4468839936,
      "rsi14": 26.7,
      "bbPercent": 0.181,
      "priceFetchedAt": "2026-06-24 00:28 EDT"
    }
  ],
  "dailyGainers": [
    {
      "ticker": "INOD",
      "percentGain": 85.75,
      "price": 84.85,
      "volume": 19182368
    },
    {
      "ticker": "RKLB",
      "percentGain": 34.44,
      "price": 105.545,
      "volume": 79927310
    },
    {
      "ticker": "FLNC",
      "percentGain": 27.36,
      "price": 24.16,
      "volume": 41472189
    },
    {
      "ticker": "AKAM",
      "percentGain": 26.58,
      "price": 147.71,
      "volume": 21492867
    },
    {
      "ticker": "EOSE",
      "percentGain": 25.94,
      "price": 8.01,
      "volume": 53900107
    },
    {
      "ticker": "FROG",
      "percentGain": 23.73,
      "price": 70.55,
      "volume": 9196270
    },
    {
      "ticker": "FLY",
      "percentGain": 22.62,
      "price": 39.68,
      "volume": 11917290
    },
    {
      "ticker": "MXL",
      "percentGain": 21.2,
      "price": 99.83,
      "volume": 7816173
    },
    {
      "ticker": "WSC",
      "percentGain": 20.6,
      "price": 28.1,
      "volume": 13336249
    },
    {
      "ticker": "RDW",
      "percentGain": 20.33,
      "price": 11.07,
      "volume": 53414126
    }
  ],
  "lastPriceRefresh": "2026-06-24 00:28 EDT",
  "dailyGainersCDN": [
    {
      "ticker": "MU.TO",
      "percentGain": 15.29,
      "price": 33.03,
      "volume": 2172888
    },
    {
      "ticker": "EXE.TO",
      "percentGain": 10.73,
      "price": 33.44,
      "volume": 1214859
    },
    {
      "ticker": "FT.TO",
      "percentGain": 9.68,
      "price": 0.17,
      "volume": 1162791
    },
    {
      "ticker": "LGD.TO",
      "percentGain": 7.91,
      "price": 1.5,
      "volume": 1470834
    },
    {
      "ticker": "BTO.TO",
      "percentGain": 7.25,
      "price": 7.25,
      "volume": 7993443
    },
    {
      "ticker": "OCG.TO",
      "percentGain": 7.25,
      "price": 0.37,
      "volume": 1282014
    },
    {
      "ticker": "RIO.TO",
      "percentGain": 6.78,
      "price": 3.15,
      "volume": 1214743
    },
    {
      "ticker": "FM.TO",
      "percentGain": 6.0,
      "price": 35,
      "volume": 4213306
    },
    {
      "ticker": "BB.TO",
      "percentGain": 5.77,
      "price": 8.8,
      "volume": 8460292
    },
    {
      "ticker": "IVN.TO",
      "percentGain": 5.64,
      "price": 11.8,
      "volume": 3629972
    }
  ],
  "recommendations": {
    "recommendations": [
      {
        "ticker": "ALAB",
        "companyName": "Alamos Gold Inc.",
        "reason": "Strong fundamentals with a high profit margin and consistent FCF. Benefiting from rising gold prices and expansion projects in production capacity.",
        "sector": "Basic Materials",
        "catalysts": [
          "Rising gold prices",
          "Successful expansion of existing mines"
        ],
        "riskLevel": "medium",
        "timeHorizon": "medium-term"
      },
      {
        "ticker": "TER",
        "companyName": "Teradyne Inc.",
        "reason": "Leader in the semiconductor test equipment market with a solid track record of growth and innovation. Benefiting from increasing demand for semiconductors across various industries.",
        "sector": "Technology",
        "catalysts": [
          "Growth in global semiconductor demand",
          "New product launches and acquisitions"
        ],
        "riskLevel": "medium",
        "timeHorizon": "long-term"
      },
      {
        "ticker": "PAAS",
        "companyName": "Pan American Silver Corp.",
        "reason": "Profitable silver mining company with a diversified portfolio of assets and strong operational performance. Benefiting from rising precious metal prices and increasing demand for industrial applications.",
        "sector": "Basic Materials",
        "catalysts": [
          "Continued growth in silver demand",
          "Exploration success and resource expansion"
        ],
        "riskLevel": "medium",
        "timeHorizon": "medium-term"
      },
      {
        "ticker": "TE",
        "companyName": "Te Connectivity Ltd.",
        "reason": "Global leader in connectivity solutions with a wide range of products serving diverse industries. Expected to benefit from increasing demand for electronic components and industrial automation.",
        "sector": "Industrials",
        "catalysts": [
          "Growth in global manufacturing",
          "Expansion into new markets"
        ],
        "riskLevel": "low",
        "timeHorizon": "medium-term"
      }
    ],
    "marketContext": "Current market conditions are characterized by rising inflation and interest rates, which may impact growth and valuations. However, opportunities exist in sectors with strong fundamentals and growth catalysts.",
    "generatedAt": "2023-10-27"
  },
  "lastUpdated": "2026-05-11 08:40 EDT",
  "opTimestamps": {
    "prices": "2026-05-11 08:26 EDT"
  }
}